[{"title":"","tag":"","name":"ブロッコリー","category":"vegetable","calory":33,"main_nutritions":["ビタミンK","ビタミンC"],"createdAt":"","href":"/ingredients/broccoli/"},{"title":"","tag":"","name":"キャベツ","category":"","calory":20,"main_nutritions":["ビタミンA"],"createdAt":"","href":"/ingredients/cabbage/"},{"title":"","tag":"","name":"レタス","category":"","calory":20,"main_nutritions":["ビタミンA"],"createdAt":"","href":"/ingredients/lettuce/"},{"title":"","tag":"","name":"玉ねぎ","category":"","calory":20,"main_nutritions":["ビタミンA"],"createdAt":"","href":"/ingredients/onion/"},{"title":"","tag":"","name":"トマト","category":"","calory":20,"main_nutritions":["ビタミンC"],"createdAt":"","href":"/ingredients/tomato/"}]